Workbook

Sheet はじめに
B2: 資産ダッシュボード 入力シート
B4: 使い方は3ステップ
B5: 1. 下のタブ（基本情報・不動産・有価証券・預貯金・その他の借入）を順に埋めます。
B6: 2. 「ファイル → 名前を変えて保存」で my-assets.xlsx として保存します（この白紙のひな形は残しておきます）。
B7: 3. このファイルを Claude とのチャットに送ります。my-assets.json に変換してお返しします。
B9: セルの色の意味
C10: 薄い黄色 ＝ あなたが入れる欄（文字は青）
C11: 薄い灰色 ＝ Excel が自動で計算する欄（さわらないでください）
B12: （例） | C12: 灰色の斜体 ＝ 書き方の見本。消しても残しても構いません（変換のとき読み飛ばします）
B14: 入力するときの決まり
B15: ・金額は「円」で入れます。1万円は 10000 です。カンマ（,）は自分で打たなくて構いません。
B16: ・「月」と書いてある欄は 1か月分の金額です。固定資産税だけは年額を入れてください（月額は自動で計算します）。
B17: ・数字は半角で入れます。全角の１２３は使えません。
B18: ・持っていない項目は 0 のままにします。行ごと消す必要はありません。
B19: ・行が足りなくなったら、一番下の行をコピーして貼り付けて増やしてください。
B21: 気をつけていただきたいこと
B22: このファイルには氏名と資産の全額が入ります。メールやクラウドに置いたままにせず、Mac の中で保管してください。
B23: GitHub には上げません（data/ フォルダは白紙のひな形と説明書以外が除外してあります）。
B25: 「検算」タブに合計と、つじつまの合わない箇所の警告が出ます。送る前に一度ご覧ください。

Sheet 基本情報
A1: 基本情報
A3: 項目 | B3: 入力 | C3: 説明
A4: 氏名 | B4: 山田 太郎 | C4: 画面の左上に出ます
A5: 基準日 | B5: 2026-09-01 | C5: いつ時点の数字か。2026-09-01 の形で入れます
A7: 為替レート
A8: 外貨を持っている場合だけ入れます。「その日のレート」を手で固定します（自動では取りません）。
A9: 通貨 | B9: 1単位あたりの円 | C9: 説明
A10: JPY | B10: 1 | C10: 日本円。1 のまま変えないでください
A11: USD | B11: 155.2 | C11: 米ドル。1ドルが何円か
C12: 他の通貨があれば（例: EUR）

Sheet 不動産
A1: 不動産 （1行に1つの物件）
A2: 灰色の「総投資額」「累計返済額」「固定資産税(月)」「月次収支」は自動で計算されます。
A4: 物件名 | B4: 住所 | C4: 広さ(㎡) | D4: 階数 | E4: 築年数 | F4: 自己資金 | G4: 当初借入額 | H4: 残債 | I4: 借入先 | J4: 金利(年%) | K4: 借入期間(年) | L4: 毎月の返済額 | M4: 家賃収入(月) | N4: 管理費(月) | O4: 修繕積立金(月) | P4: 固定資産税(年額) | Q4: 総投資額 | R4: 累計返済額 | S4: 固定資産税(月) | T4: 月次収支
A5: （例）物件A | B5: 東京都港区白金台 | C5: 45.5 | D5: 3 / 10 階 | E5: 15 | F5: 10000000 | G5: 40000000 | H5: 35500000 | I5: A銀行 | J5: 1.8 | K5: 35 | L5: 128000 | M5: 180000 | N5: 12000 | O5: 8000 | P5: 108000 | Q5: =F5+G5 -> 50000000 | R5: =G5-H5 -> 4500000 | S5: =ROUND(P5/12,0) -> 9000 | T5: =M5-L5-N5-O5-S5 -> 23000
Q6: =F6+G6 -> 0 | R6: =G6-H6 -> 0 | S6: =ROUND(P6/12,0) -> 0 | T6: =M6-L6-N6-O6-S6 -> 0
Q7: =F7+G7 -> 0 | R7: =G7-H7 -> 0 | S7: =ROUND(P7/12,0) -> 0 | T7: =M7-L7-N7-O7-S7 -> 0
Q8: =F8+G8 -> 0 | R8: =G8-H8 -> 0 | S8: =ROUND(P8/12,0) -> 0 | T8: =M8-L8-N8-O8-S8 -> 0
Q9: =F9+G9 -> 0 | R9: =G9-H9 -> 0 | S9: =ROUND(P9/12,0) -> 0 | T9: =M9-L9-N9-O9-S9 -> 0
Q10: =F10+G10 -> 0 | R10: =G10-H10 -> 0 | S10: =ROUND(P10/12,0) -> 0 | T10: =M10-L10-N10-O10-S10 -> 0
Q11: =F11+G11 -> 0 | R11: =G11-H11 -> 0 | S11: =ROUND(P11/12,0) -> 0 | T11: =M11-L11-N11-O11-S11 -> 0
Q12: =F12+G12 -> 0 | R12: =G12-H12 -> 0 | S12: =ROUND(P12/12,0) -> 0 | T12: =M12-L12-N12-O12-S12 -> 0
Q13: =F13+G13 -> 0 | R13: =G13-H13 -> 0 | S13: =ROUND(P13/12,0) -> 0 | T13: =M13-L13-N13-O13-S13 -> 0
Q14: =F14+G14 -> 0 | R14: =G14-H14 -> 0 | S14: =ROUND(P14/12,0) -> 0 | T14: =M14-L14-N14-O14-S14 -> 0
A16: ※ 行が足りないときは、最終行（14行目）をコピーして下に貼り付けてください。数式も一緒に増えます。

Sheet 有価証券
A1: 有価証券 （国内・海外 × 4種類 ＝ 8行で固定）
A2: 持っていない種類は 0 のままにします（行は消しません。入れ忘れに気づけるようにするためです）。
A3: 「その他」は暗号資産・金・銀などをまとめる欄です。金額はその通貨のままで入れます（円換算は自動）。
A5: 地域 | B5: 種類 | C5: 通貨 | D5: 取得原価 | E5: 評価額 | F5: 補足（任意） | G5: 含み損益 | H5: 円換算した評価額
A6: 国内 | B6: 株 | C6: JPY | D6: 2000000 | E6: 5000000 | G6: =E6-D6 -> 3000000 | H6: =ROUND(E6*IFERROR(INDEX(基本情報!$B$10:$B$13,MATCH(C6,基本情報!$A$10:$A$13,0)),0),0) -> 5000000
A7: 国内 | B7: 債券 | C7: JPY | D7: 2700000 | E7: 2500000 | G7: =E7-D7 -> -200000 | H7: =ROUND(E7*IFERROR(INDEX(基本情報!$B$10:$B$13,MATCH(C7,基本情報!$A$10:$A$13,0)),0),0) -> 2500000
A8: 国内 | B8: 投資信託 | C8: JPY | D8: 1300000 | E8: 1500000 | G8: =E8-D8 -> 200000 | H8: =ROUND(E8*IFERROR(INDEX(基本情報!$B$10:$B$13,MATCH(C8,基本情報!$A$10:$A$13,0)),0),0) -> 1500000
A9: 国内 | B9: その他 | C9: JPY | D9: 800000 | E9: 1200000 | F9: 金地金 | G9: =E9-D9 -> 400000 | H9: =ROUND(E9*IFERROR(INDEX(基本情報!$B$10:$B$13,MATCH(C9,基本情報!$A$10:$A$13,0)),0),0) -> 1200000
A10: 海外 | B10: 株 | C10: USD | D10: 20000 | E10: 32000 | G10: =E10-D10 -> 12000 | H10: =ROUND(E10*IFERROR(INDEX(基本情報!$B$10:$B$13,MATCH(C10,基本情報!$A$10:$A$13,0)),0),0) -> 4966400
A11: 海外 | B11: 債券 | C11: USD | D11: 18000 | E11: 16000 | G11: =E11-D11 -> -2000 | H11: =ROUND(E11*IFERROR(INDEX(基本情報!$B$10:$B$13,MATCH(C11,基本情報!$A$10:$A$13,0)),0),0) -> 2483200
A12: 海外 | B12: 投資信託 | C12: USD | D12: 8000 | E12: 9500 | G12: =E12-D12 -> 1500 | H12: =ROUND(E12*IFERROR(INDEX(基本情報!$B$10:$B$13,MATCH(C12,基本情報!$A$10:$A$13,0)),0),0) -> 1474400
A13: 海外 | B13: その他 | C13: USD | D13: 5000 | E13: 11000 | F13: 暗号資産 | G13: =E13-D13 -> 6000 | H13: =ROUND(E13*IFERROR(INDEX(基本情報!$B$10:$B$13,MATCH(C13,基本情報!$A$10:$A$13,0)),0),0) -> 1707200
A14: 合計 | D14: =SUM(D6:D13) -> 6851000 | E14: =SUM(E6:E13) -> 10268500 | F14: ※ 通貨が違うので、この行の取得原価と評価額の合計は目安です） | G14: =SUM(G6:G13) -> 3417500 | H14: =SUM(H6:H13) -> 20831200

Sheet 預貯金
A1: 預貯金 （1行に1つの口座）
A2: 同じ銀行に複数口座があるときは、まとめて1行にしても、分けて書いても構いません。
A4: 金融機関 | B4: 通貨 | C4: 残高 | D4: 円換算した残高
A5: （例）A銀行 | B5: JPY | C5: 2000000 | D5: =IF(A5="","",ROUND(C5*IFERROR(INDEX(基本情報!$B$10:$B$13,MATCH(B5,基本情報!$A$10:$A$13,0)),0),0)) -> 2000000
D6: =IF(A6="","",ROUND(C6*IFERROR(INDEX(基本情報!$B$10:$B$13,MATCH(B6,基本情報!$A$10:$A$13,0)),0),0))
D7: =IF(A7="","",ROUND(C7*IFERROR(INDEX(基本情報!$B$10:$B$13,MATCH(B7,基本情報!$A$10:$A$13,0)),0),0))
D8: =IF(A8="","",ROUND(C8*IFERROR(INDEX(基本情報!$B$10:$B$13,MATCH(B8,基本情報!$A$10:$A$13,0)),0),0))
D9: =IF(A9="","",ROUND(C9*IFERROR(INDEX(基本情報!$B$10:$B$13,MATCH(B9,基本情報!$A$10:$A$13,0)),0),0))
D10: =IF(A10="","",ROUND(C10*IFERROR(INDEX(基本情報!$B$10:$B$13,MATCH(B10,基本情報!$A$10:$A$13,0)),0),0))
D11: =IF(A11="","",ROUND(C11*IFERROR(INDEX(基本情報!$B$10:$B$13,MATCH(B11,基本情報!$A$10:$A$13,0)),0),0))
D12: =IF(A12="","",ROUND(C12*IFERROR(INDEX(基本情報!$B$10:$B$13,MATCH(B12,基本情報!$A$10:$A$13,0)),0),0))
D13: =IF(A13="","",ROUND(C13*IFERROR(INDEX(基本情報!$B$10:$B$13,MATCH(B13,基本情報!$A$10:$A$13,0)),0),0))
D14: =IF(A14="","",ROUND(C14*IFERROR(INDEX(基本情報!$B$10:$B$13,MATCH(B14,基本情報!$A$10:$A$13,0)),0),0))
D15: =IF(A15="","",ROUND(C15*IFERROR(INDEX(基本情報!$B$10:$B$13,MATCH(B15,基本情報!$A$10:$A$13,0)),0),0))
D16: =IF(A16="","",ROUND(C16*IFERROR(INDEX(基本情報!$B$10:$B$13,MATCH(B16,基本情報!$A$10:$A$13,0)),0),0))
D17: =IF(A17="","",ROUND(C17*IFERROR(INDEX(基本情報!$B$10:$B$13,MATCH(B17,基本情報!$A$10:$A$13,0)),0),0))
... D19: =IF(A19="","",ROUND(C19*IFERROR(INDEX(基本情報!$B$10:$B$13,MATCH(B19,基本情報!$A$10:$A$13,0)),0),0))
A20: 合計（見本行は数えません） | D20: =SUM(D6:D19) -> 0

Sheet その他の借入
A1: 不動産以外の借入 （1行に1つのローン）
A2: 車のローン、教育ローン、多目的ローンなど。不動産のローンは「不動産」タブに書くので、ここには書きません。
A3: 借入がなければ、すべて空のままで構いません。
A5: 借入の名前 | B5: 種類 | C5: 借入先 | D5: 当初借入額 | E5: 残債 | F5: 金利(年%) | G5: 毎月の返済額 | H5: 返済済み
A6: （例）自動車ローン | B6: 車 | C6: D銀行 | D6: 3000000 | E6: 1800000 | F6: 2.5 | G6: 45000 | H6: =IF(A6="","",D6-E6) -> 1200000
H7: =IF(A7="","",D7-E7)
H8: =IF(A8="","",D8-E8)
H9: =IF(A9="","",D9-E9)
H10: =IF(A10="","",D10-E10)
H11: =IF(A11="","",D11-E11)
H12: =IF(A12="","",D12-E12)
H13: =IF(A13="","",D13-E13)
H14: =IF(A14="","",D14-E14)
H15: =IF(A15="","",D15-E15)

Sheet 検算
A1: 検算 （自動計算。送る前にここを見てください）
A2: この表はすべて自動です。画面に出る数字と同じものを先に確かめられます。
A4: 金融資産
A5: 有価証券（評価額・円） | B5: =有価証券!H14 -> 20831200 | C5: 円換算した評価額の合計
A6: うち含み損益 | B6: =有価証券!H14-SUMPRODUCT(有価証券!D6:D13,IFERROR(INDEX(基本情報!$B$10:$B$13,MATCH(有価証券!C6:C13,基本情報!$A$10:$A$13,0)),0)) -> 6116000 | C6: 評価額 − 取得原価
A7: 預貯金 | B7: =預貯金!D20 -> 0 | C7: 円換算した残高の合計
A8: 金融資産合計 | B8: =有価証券!H14+預貯金!D20 -> 20831200 | C8: 有価証券 ＋ 預貯金（不動産は含めません）
A10: 不動産
A11: 総投資額 | B11: =SUM(不動産!$Q$6:$Q$14) -> 0 | C11: 自己資金 ＋ 当初借入額
A12: 自己資金累計 | B12: =SUM(不動産!$F$6:$F$14) -> 0
A13: 借入総額 | B13: =SUM(不動産!$G$6:$G$14) -> 0 | C13: 当初の借入額の合計
A14: 残債合計 | B14: =SUM(不動産!$H$6:$H$14) -> 0
A15: 累計返済額 | B15: =SUM(不動産!$R$6:$R$14) -> 0 | C15: 借入総額 − 残債合計
A16: 返済進捗率 | B16: =IFERROR(SUM(不動産!$R$6:$R$14)/SUM(不動産!$G$6:$G$14),0) -> 0 | C16: 累計返済額 ÷ 借入総額
A17: 月次収支の合計 | B17: =SUM(不動産!$T$6:$T$14) -> 0 | C17: 家賃 − 返済 − 経費。マイナスなら持ち出しです
A19: 負債
A20: 不動産ローン 残債 | B20: =SUM(不動産!$H$6:$H$14) -> 0
A21: その他の借入 残債 | B21: =SUM(その他の借入!E7:E15) -> 0 | C21: 車・多目的など
A22: 総負債 | B22: =SUM(不動産!$H$6:$H$14)+SUM(その他の借入!E7:E15) -> 0 | C22: 不動産 ＋ その他
A25: つじつまの確認
A26: 「要確認」が出たら、その行の説明どおりに直してください。
A27: 残債が当初借入額より大きい物件 | B27: =IF(SUMPRODUCT((不動産!A6:A14<>"")*(不動産!H6:H14>不動産!G6:G14))>0,"要確認","OK") -> OK | C27: 残債は当初借入額以下になるはずです
A28: 残債が当初借入額より大きい借入 | B28: =IF(SUMPRODUCT((その他の借入!A7:A15<>"")*(その他の借入!E7:E15>その他の借入!D7:D15))>0,"要確認","OK") -> OK | C28: 同上
A29: マイナスの金額が入っている | B29: =IF(SUMPRODUCT((不動産!F6:H14<0)*1)+SUMPRODUCT((有価証券!D6:E13<0)*1)>0,"要確認","OK") -> OK | C29: 金額はすべて 0 以上で入れます
A30: 為替レートの無い通貨がある | B30: =IF(SUMPRODUCT(ISERROR(MATCH(有価証券!C6:C13,基本情報!$A$10:$A$13,0))*1)>0,"要確認","OK") -> OK | C30: 「基本情報」タブの為替レートに、使った通貨を足してください
A31: 氏名と基準日が入っている | B31: =IF(OR(基本情報!B4="",基本情報!B5=""),"要確認","OK") -> OK | C31: どちらも必須です
